LICENSE
MANIFEST.in
README.md
engines.ini
setup.py
polyarchiv/__init__.py
polyarchiv/backends.py
polyarchiv/backup_points.py
polyarchiv/cli.py
polyarchiv/collect_points.py
polyarchiv/conf.py
polyarchiv/config_checks.py
polyarchiv/filelocks.py
polyarchiv/filters.py
polyarchiv/hooks.py
polyarchiv/points.py
polyarchiv/runner.py
polyarchiv/sources.py
polyarchiv/termcolor.py
polyarchiv/utils.py
polyarchiv/visitors.py
polyarchiv.egg-info/PKG-INFO
polyarchiv.egg-info/SOURCES.txt
polyarchiv.egg-info/dependency_links.txt
polyarchiv.egg-info/entry_points.txt
polyarchiv.egg-info/not-zip-safe
polyarchiv.egg-info/requires.txt
polyarchiv.egg-info/top_level.txt
polyarchiv/_vendor/__init__.py
polyarchiv/_vendor/ldif3.py
polyarchiv/_vendor/lru_cache.py
polyarchiv/_vendor/requests.py
polyarchiv/_vendor/requests/__init__.py
polyarchiv/_vendor/requests/_internal_utils.py
polyarchiv/_vendor/requests/adapters.py
polyarchiv/_vendor/requests/api.py
polyarchiv/_vendor/requests/auth.py
polyarchiv/_vendor/requests/certs.py
polyarchiv/_vendor/requests/compat.py
polyarchiv/_vendor/requests/cookies.py
polyarchiv/_vendor/requests/exceptions.py
polyarchiv/_vendor/requests/hooks.py
polyarchiv/_vendor/requests/models.py
polyarchiv/_vendor/requests/sessions.py
polyarchiv/_vendor/requests/status_codes.py
polyarchiv/_vendor/requests/structures.py
polyarchiv/_vendor/requests/utils.py
polyarchiv/_vendor/requests/packages/__init__.py
polyarchiv/_vendor/requests/packages/chardet/__init__.py
polyarchiv/_vendor/requests/packages/chardet/big5freq.py
polyarchiv/_vendor/requests/packages/chardet/big5prober.py
polyarchiv/_vendor/requests/packages/chardet/chardetect.py
polyarchiv/_vendor/requests/packages/chardet/chardistribution.py
polyarchiv/_vendor/requests/packages/chardet/charsetgroupprober.py
polyarchiv/_vendor/requests/packages/chardet/charsetprober.py
polyarchiv/_vendor/requests/packages/chardet/codingstatemachine.py
polyarchiv/_vendor/requests/packages/chardet/compat.py
polyarchiv/_vendor/requests/packages/chardet/constants.py
polyarchiv/_vendor/requests/packages/chardet/cp949prober.py
polyarchiv/_vendor/requests/packages/chardet/escprober.py
polyarchiv/_vendor/requests/packages/chardet/escsm.py
