Metadata-Version: 1.1
Name: polyarchiv
Version: 0.14.3
Summary: Multiple-source backup tool: backup files|MySQL|LDAP|PostgresSQL to git|rsync|tar archives
Home-page: https://github.com/d9pouces/Polyarchiv
Author: Matthieu Gallet
Author-email: mgallet@19pouces.net
License: CeCILL-B
Platform: UNKNOWN
Classifier: Development Status :: 4 - Beta
Classifier: Operating System :: MacOS :: MacOS X
Classifier: Operating System :: POSIX :: BSD
Classifier: Operating System :: POSIX :: Linux
Classifier: Operating System :: Unix
Classifier: License :: OSI Approved :: CEA CNRS Inria Logiciel Libre License, version 2.1 (CeCILL-2.1)
Classifier: Programming Language :: Python :: 2.7
Classifier: Programming Language :: Python :: 3.3
Classifier: Programming Language :: Python :: 3.4
Classifier: Programming Language :: Python :: 3.5
